fifo_memory.v
module fifo_memory #(
    parameter ADDR_SIZE = 3,
    parameter DEPTH = 8,
    parameter DATA_SIZE = 8
  )(
    input clk, rst,
    input [DEPTH-1:0] data_in,
    input WE, RE,
    output reg [DEPTH-1:0] data_out
  );

  reg [DEPTH-1:0] mem [DATA_SIZE-1:0];
  reg [ADDR_SIZE-1:0] rd_ptr, wr_ptr,rd_addr, wr_addr;
  integer N;
  reg [1:0] st;

  integer i;

  always @(posedge clk or negedge rst)
  begin : FIFO_MEMORY
    if (~rst)
    begin
      for (i = 0 ; i < DEPTH; i = i + 1)
      begin
        mem[i] <= 8'b00000000;
      end
      data_out = 8'b00000000;
      rd_ptr = 3'b000;
      wr_ptr = 3'b000;
      N = 0;
      st = 2'b00;
    end
    else
    begin
      if (RE)
      begin : READ_CONTROLLER
        if (~st[1])
        begin
          data_out <= mem[rd_ptr];
          rd_ptr <= (rd_ptr + 1) % DEPTH;
          N = N - 1;
        end
      end

      if (WE)
      begin : WRITE_CONTROLLER
        if (~st[0])
        begin
          mem[wr_ptr] <= data_in;
          wr_ptr <= (wr_ptr + 1) % DEPTH;
          N = N + 1;
        end
      end

      begin : FIFO_CONTROLLER
        if (N == 0)
          st <= 2'b10;
        else if (N == DEPTH)
          st <= 2'b01;
        else
          st <= 2'b00;
      end

    end
  end

endmodule

fifo_memory_tb.v
module fifo_memory_tb;
  parameter ADDR_SIZE = 3;
  parameter DEPTH = 8;
  parameter DATA_SIZE = 8;

  reg clk;
  reg rst;
  reg [DEPTH-1:0] data_in;
  reg WE;
  reg RE;
  wire [DEPTH-1:0] data_out;

  reg [DEPTH-1:0] data = 0;
  reg [ADDR_SIZE-1:0]temp_rd_ptr;

  fifo_memory #(
                .ADDR_SIZE(ADDR_SIZE),
                .DEPTH(DEPTH),
                .DATA_SIZE(DATA_SIZE)
              ) dut (
                .clk(clk),
                .rst(rst),
                .data_in(data_in),
                .WE(WE),
                .RE(RE),
                .data_out(data_out)
              );

  always
  begin
    #5 clk = ~clk;
  end

  initial
  begin
    $dumpfile("fifo_memory_waveform.vcd");
    $dumpvars(0, fifo_memory_tb);
    $display("Starting FIFO Memory Controller Testbench");

    clk = 0;
    rst = 1;
    data_in = 8'h00;
    WE = 0;
    RE = 0;

    #10;
    rst = 0;
    #10;

    // Write 9 data to the FIFO, last one will fail as FIFO is full
    repeat (9)
    begin
      WE = 1;
      data = data +1;
      data_in = data;
      #10;
    end
    WE = 0;
    data_in = 8'h00;

    #10;

    // Read 3 data from the FIFO
    repeat (3)
    begin
      RE = 1;
      #10;
    end
    RE = 0;
    #10;

    // Write 3 data to the FIFO, it will start again from zero
    // as last time the write pointer had reached last memory location (0x07)
    repeat (4)
    begin
      WE = 1;
      data = data +1;
      data_in = data;
      #10;
    end
    WE = 0;
    data_in = 8'h00;

    // Read 9 data from the FIFO, 9th will fail as after 8 reads FIFO will be empty
    repeat (9)
    begin
      RE = 1;
      #10;
    end
    RE = 0;
    #10;

    //Check simultaneous read and write
    WE = 1;
    data = data +1;
    data_in = data;
    #10;
    repeat (4)
    begin
      RE = 1;
      data = data +1;
      data_in = data;
      #10;
    end
    WE = 0;
    RE = 0;
    data_in = 8'h00;

    #10;
    $finish;
  end

  always @(posedge clk)
  begin
    if (RE)
    begin
      if (dut.st[1])
        $display("Reading Data: Can't read data, FIFO memory empty\n");
      else
      begin
        temp_rd_ptr = dut.rd_ptr;
        #5;
        $display("Reading Data: data_out = Ox%h from rd_ptr = %b, st = %b\n", data_out, temp_rd_ptr, dut.st);

      end
    end
    if (WE)
    begin
      if (dut.st[0])
        $display("Writing Data: Can't write data, FIFO memory full\n");
      else
        $display("Writing Data: data_in = Ox%h, at wr_ptr = %b,  st = %b\n", data_in, dut.wr_ptr, dut.st );
    end
  end

endmodule

fifo_memory_waveform.vcd
$date
	Thu Sep 14 09:06:27 2023
$end
$version
	Icarus Verilog
$end
$timescale
	1s
$end
$scope module fifo_memory_tb $end
$var wire 8 ! data_out [7:0] $end
$var parameter 32 " ADDR_SIZE $end
$var parameter 32 # DATA_SIZE $end
$var parameter 32 $ DEPTH $end
$var reg 1 % RE $end
$var reg 1 & WE $end
$var reg 1 ' clk $end
$var reg 8 ( data [7:0] $end
$var reg 8 ) data_in [7:0] $end
$var reg 1 * rst $end
$var reg 3 + temp_rd_ptr [2:0] $end
$scope module dut $end
$var wire 1 % RE $end
$var wire 1 & WE $end
$var wire 1 ' clk $end
$var wire 8 , data_in [7:0] $end
$var wire 1 * rst $end
$var parameter 32 - ADDR_SIZE $end
$var parameter 32 . DATA_SIZE $end
$var parameter 32 / DEPTH $end
$var reg 8 0 data_out [7:0] $end
$var reg 3 1 rd_ptr [2:0] $end
$var reg 2 2 st [1:0] $end
$var reg 3 3 wr_ptr [2:0] $end
$var integer 32 4 N [31:0] $end
$var integer 32 5 i [31:0] $end
$scope begin FIFO_MEMORY $end
$scope begin FIFO_CONTROLLER $end
$upscope $end
$scope begin READ_CONTROLLER $end
$upscope $end
$scope begin WRITE_CONTROLLER $end
$upscope $end
$upscope $end
$upscope $end
$upscope $end
$enddefinitions $end
$comment Show the parameter values. $end
$dumpall
b1000 /
b1000 .
b11 -
b1000 $
b1000 #
b11 "
$end
#0
$dumpvars
bx 5
bx 4
bx 3
bx 2
bx 1
bx 0
b0 ,
bx +
1*
b0 )
b0 (
0'
0&
0%
bx !
$end
#5
b0 2
b0 4
b0 3
b0 1
b0 !
b0 0
b1000 5
1'
#10
0'
0*
#15
b10 2
1'
#20
0'
b1 )
b1 ,
b1 (
1&
#25
b0 2
b1 3
b1 4
1'
#30
0'
b10 )
b10 ,
b10 (
#35
b10 3
b10 4
1'
#40
0'
b11 )
b11 ,
b11 (
#45
b11 3
b11 4
1'
#50
0'
b100 )
b100 ,
b100 (
#55
b100 3
b100 4
1'
#60
0'
b101 )
b101 ,
b101 (
#65
b101 3
b101 4
1'
#70
0'
b110 )
b110 ,
b110 (
#75
b110 3
b110 4
1'
#80
0'
b111 )
b111 ,
b111 (
#85
b111 3
b111 4
1'
#90
0'
b1000 )
b1000 ,
b1000 (
#95
b1 2
b0 3
b1000 4
1'
#100
0'
b1001 )
b1001 ,
b1001 (
#105
1'
#110
0'
b0 )
b0 ,
0&
#115
1'
#120
0'
1%
#125
b0 2
b1 1
b1 !
b1 0
b111 4
b0 +
1'
#130
0'
#135
b10 1
b10 !
b10 0
b110 4
b1 +
1'
#140
0'
#145
b11 1
b11 !
b11 0
b101 4
b10 +
1'
#150
0'
0%
#155
1'
#160
0'
b1010 )
b1010 ,
b1010 (
1&
#165
b1 3
b110 4
1'
#170
0'
b1011 )
b1011 ,
b1011 (
#175
b10 3
b111 4
1'
#180
0'
b1100 )
b1100 ,
b1100 (
#185
b1 2
b11 3
b1000 4
1'
#190
0'
b1101 )
b1101 ,
b1101 (
#195
1'
#200
0'
1%
b0 )
b0 ,
0&
#205
b0 2
b100 1
b100 !
b100 0
b111 4
b11 +
1'
#210
0'
#215
b101 1
b101 !
b101 0
b110 4
b100 +
1'
#220
0'
#225
b110 1
b110 !
b110 0
b101 4
b101 +
1'
#230
0'
#235
b111 1
b111 !
b111 0
b100 4
b110 +
1'
#240
0'
#245
b0 1
b1000 !
b1000 0
b11 4
b111 +
1'
#250
0'
#255
b1 1
b1010 !
b1010 0
b10 4
b0 +
1'
#260
0'
#265
b10 1
b1011 !
b1011 0
b1 4
b1 +
1'
#270
0'
#275
b10 2
b11 1
b1100 !
b1100 0
b0 4
b10 +
1'
#280
0'
#285
1'
#290
0'
0%
#295
1'
#300
0'
b1110 )
b1110 ,
b1110 (
1&
#305
b0 2
b100 3
b1 4
1'
#310
0'
b1111 )
b1111 ,
b1111 (
1%
#315
b101 3
b100 1
b1110 !
b1110 0
b1 4
b11 +
1'
#320
0'
b10000 )
b10000 ,
b10000 (
#325
b110 3
b101 1
b1111 !
b1111 0
b1 4
b100 +
1'
#330
0'
b10001 )
b10001 ,
b10001 (
#335
b111 3
b110 1
b10000 !
b10000 0
b1 4
b101 +
1'
#340
0'
b10010 )
b10010 ,
b10010 (
#345
b0 3
b111 1
b10001 !
b10001 0
b1 4
b110 +
1'
#350
0'
b0 )
b0 ,
0%
0&
